sdg_core_lib/__init__.py
sdg_core_lib/browser.py
sdg_core_lib/commons.py
sdg_core_lib/config.py
sdg_core_lib/data_generator/__init__.py
sdg_core_lib/data_generator/model_factory.py
sdg_core_lib/data_generator/models/ModelInfo.py
sdg_core_lib/data_generator/models/TrainingInfo.py
sdg_core_lib/data_generator/models/UnspecializedModel.py
sdg_core_lib/data_generator/models/__init__.py
sdg_core_lib/data_generator/models/keras/KerasBaseVAE.py
sdg_core_lib/data_generator/models/keras/VAE.py
sdg_core_lib/data_generator/models/keras/__init__.py
sdg_core_lib/data_generator/models/keras/implementation/AutoTabularVAE.py
sdg_core_lib/data_generator/models/keras/implementation/TabularVAE.py
sdg_core_lib/data_generator/models/keras/implementation/TimeSeriesVAE.py
sdg_core_lib/data_generator/models/keras/implementation/__init__.py
sdg_core_lib/dataset/__init__.py
sdg_core_lib/dataset/columns.py
sdg_core_lib/dataset/datasets.py
sdg_core_lib/dataset/processor.py
sdg_core_lib/dataset/steps.py
sdg_core_lib/evaluate/__init__.py
sdg_core_lib/evaluate/metrics.py
sdg_core_lib/evaluate/tables.py
sdg_core_lib/evaluate/time_series.py
sdg_core_lib/job.py
sdg_core_lib/post_process/FunctionApplier.py
sdg_core_lib/post_process/__init__.py
sdg_core_lib/post_process/function_factory.py
sdg_core_lib/post_process/function_utils.py
sdg_core_lib/post_process/functions/Parameter.py
sdg_core_lib/post_process/functions/UnspecializedFunction.py
sdg_core_lib/post_process/functions/__init__.py
sdg_core_lib/post_process/functions/distribution_evaluator/__init__.py
sdg_core_lib/post_process/functions/distribution_evaluator/implementation/NormalTester.py
sdg_core_lib/post_process/functions/distribution_evaluator/implementation/__init__.py
sdg_core_lib/post_process/functions/filter/IntervalThreshold.py
sdg_core_lib/post_process/functions/filter/MonoThreshold.py
sdg_core_lib/post_process/functions/filter/__init__.py
sdg_core_lib/post_process/functions/filter/implementation/InnerThreshold.py
sdg_core_lib-0.1.6.dist-info/WHEEL
sdg_core_lib-0.1.6.dist-info/entry_points.txt
sdg_core_lib-0.1.6.dist-info/METADATA
sdg_core_lib-0.1.6.dist-info/RECORD
