Metadata-Version: 2.3
Name: sdg-core-lib
Version: 0.1.6
Summary: Add your description here
Author: emiliocimino
Author-email: emiliocimino <emilio.cimino@outlook.it>
Requires-Dist: numpy==2.0.2
Requires-Dist: pandas==2.2.3
Requires-Dist: seaborn==0.13.2
Requires-Dist: scikit-learn==1.5.2
Requires-Dist: keras==3.6.0
Requires-Dist: tensorflow==2.18.0
Requires-Dist: loguru==0.7.3
Requires-Dist: skops==0.13.0
Requires-Dist: statsmodels==0.14.5
Requires-Dist: tslearn==0.7.0
Requires-Dist: keras-tuner==1.4.8
Requires-Python: >=3.12
